django_auth_adfs_db/__init__.py
django_auth_adfs_db/admin.py
django_auth_adfs_db/apps.py
django_auth_adfs_db/backends.py
django_auth_adfs_db/models.py
django_auth_adfs_db/settings.py
django_auth_adfs_db/migrations/0001_initial.py
django_auth_adfs_db/migrations/0002_adfsconfig_sync_groups.py
django_auth_adfs_db/migrations/0003_auto_20210323_1441.py
django_auth_adfs_db/migrations/__init__.py
django_auth_adfs_db-0.3.0.dist-info/LICENSE
django_auth_adfs_db-0.3.0.dist-info/METADATA
django_auth_adfs_db-0.3.0.dist-info/WHEEL
django_auth_adfs_db-0.3.0.dist-info/top_level.txt
django_auth_adfs_db-0.3.0.dist-info/RECORD
