Metadata-Version: 2.1
Name: django-auth-adfs-db
Version: 0.3.0
Summary: A database-backed django-auth-adfs settings class
Home-page: https://github.com/isprojects/django-auth-adfs-db
Author: ISProjects B.V., Sergei Maertens, Maykin Media
Author-email: info@isprojects.nl
License: MIT
Keywords: ADFS,Django,database,authentication backend
Platform: UNKNOWN
Classifier: Development Status :: 4 - Beta
Classifier: Framework :: Django
Classifier: Framework :: Django :: 2.2
Classifier: Framework :: Django :: 3.1
Classifier: Intended Audience :: Developers
Classifier: Operating System :: Unix
Classifier: Operating System :: MacOS
Classifier: Operating System :: Microsoft :: Windows
Classifier: Programming Language :: Python :: 3.6
Classifier: Programming Language :: Python :: 3.7
Classifier: Programming Language :: Python :: 3.8
Classifier: Programming Language :: Python :: 3.9
Classifier: Topic :: Software Development :: Libraries :: Python Modules
Requires-Dist: django
Requires-Dist: django-auth-adfs
Requires-Dist: django-solo
Provides-Extra: coverage
Requires-Dist: pytest-cov ; extra == 'coverage'
Provides-Extra: docs
Requires-Dist: sphinx ; extra == 'docs'
Requires-Dist: sphinx-rtd-theme ; extra == 'docs'
Provides-Extra: release
Requires-Dist: bumpversion ; extra == 'release'
Provides-Extra: tests
Requires-Dist: psycopg2 ; extra == 'tests'
Requires-Dist: pytest ; extra == 'tests'
Requires-Dist: pytest-django ; extra == 'tests'
Requires-Dist: tox ; extra == 'tests'
Requires-Dist: isort ; extra == 'tests'
Requires-Dist: black ; extra == 'tests'
